{
    "version": "9.2.0-rc2",
    "description": "A generic and open source machine emulator and virtualizer.",
    "homepage": "https://qemu.weilnetz.de/",
    "license": "GPL-2.0-only",
    "architecture": {
        "64bit": {
            "url": "https://qemu.weilnetz.de/w64/2024/qemu-w64-setup-20241219.exe#/dl.7z_",
            "hash": "sha512:959e45bdde65def2e6870e729425ed21e2ca8a9b5da0c1c74f2da43b15288d3e7f0ae46b633050663d8beeab6d8e9bc3c682276a1f62b74c64143fab994a1c4c"
        }
    },
    "pre_install": "Expand-7zipArchive \"$dir\\dl.7z_\" \"$dir\" -Removal -Switches '-xr!*.exe.nsis -x!$PLUGINSDIR'",
    "env_add_path": ".",
    "checkver": "<strong>(?<year>\\d{4})-(?<month>\\d{2})-(?<day>\\d{2})</strong>: New QEMU installer \\((?<version>[\\d.a-z-]+)\\)",
    "autoupdate": {
        "architecture": {
            "64bit": {
                "url": "https://qemu.weilnetz.de/w64/$matchYear/qemu-w64-setup-$matchYear$matchMonth$matchDay.exe#/dl.7z_"
            }
        },
        "hash": {
            "url": "$urlNoExt.sha512"
        }
    }
}
